PySimultan2/CHANGELOG.md
PySimultan2/__about__.py
PySimultan2/__init__.py
PySimultan2/data_model.py
PySimultan2/default_types.py
PySimultan2/files.py
PySimultan2/multi_values.py
PySimultan2/object_mapper.py
PySimultan2/simultan_object.py
PySimultan2/taxonomy_maps.py
PySimultan2/type_setter_lookup.py
PySimultan2/utils.py
PySimultan2/geometry/__init__.py
PySimultan2/geometry/geometry_base.py
PySimultan2/geometry/utils.py
PySimultan2/resources/ClosedXML.dll
PySimultan2/resources/ControlzEx.dll
PySimultan2/resources/DocumentFormat.OpenXml.dll
PySimultan2/resources/DotSpatial.Projections.dll
PySimultan2/resources/ExcelNumberFormat.dll
PySimultan2/resources/Fluent.dll
PySimultan2/resources/MathNet.Numerics.dll
PySimultan2/resources/Microsoft.AspNetCore.Authorization.dll
PySimultan2/resources/Microsoft.AspNetCore.Metadata.dll
PySimultan2/resources/Microsoft.Extensions.DependencyInjection.Abstractions.dll
PySimultan2/resources/Microsoft.Extensions.Logging.Abstractions.dll
PySimultan2/resources/Microsoft.Extensions.Options.dll
PySimultan2/resources/Microsoft.Extensions.Primitives.dll
PySimultan2/resources/Microsoft.WindowsAPICodePack.Shell.dll
PySimultan2/resources/Microsoft.WindowsAPICodePack.dll
PySimultan2/resources/Microsoft.Xaml.Behaviors.dll
PySimultan2/resources/Newtonsoft.Json.Bson.dll
PySimultan2/resources/Newtonsoft.Json.dll
PySimultan2/resources/SIMULTAN.Lang.dll
PySimultan2/resources/SIMULTAN.Lang.xml
PySimultan2/resources/SIMULTAN.Plugins.dll
PySimultan2/resources/SIMULTAN.Plugins.xml
PySimultan2/resources/SIMULTAN.dll
PySimultan2/resources/SIMULTAN.xml
PySimultan2/resources/SharpDX.Mathematics.dll
PySimultan2/resources/Sprache.Calc.dll
PySimultan2/resources/Sprache.dll
PySimultan2/resources/System.Data.OleDb.dll
PySimultan2/resources/System.Net.Http.Formatting.dll
PySimultan2/resources/System.Reflection.MetadataLoadContext.dll
PySimultan2/resources/__init__.py
pysimultan-0.7.5.dist-info/METADATA
pysimultan-0.7.5.dist-info/WHEEL
pysimultan-0.7.5.dist-info/licenses/LICENSE.txt
pysimultan-0.7.5.dist-info/RECORD
