Metadata-Version: 2.4
Name: PySimultan
Version: 0.7.5
Project-URL: Documentation, https://github.com/BÃ¼hler Maximilian/PySimultan2#readme
Project-URL: Issues, https://github.com/BÃ¼hler Maximilian/PySimultan2/issues
Project-URL: Source, https://github.com/BÃ¼hler Maximilian/PySimultan2
Author-email: BÃ¼hler Maximilian <maximilian.buehler@tuwien.ac.at>
License-Expression: MIT
License-File: LICENSE.txt
Classifier: Development Status :: 4 - Beta
Classifier: Programming Language :: Python
Classifier: Programming Language :: Python :: 3.8
Classifier: Programming Language :: Python :: 3.9
Classifier: Programming Language :: Python :: 3.10
Classifier: Programming Language :: Python :: 3.11
Classifier: Programming Language :: Python :: 3.12
Classifier: Programming Language :: Python :: Implementation :: CPython
Classifier: Programming Language :: Python :: Implementation :: PyPy
Requires-Python: >=3.8
Requires-Dist: colorlog
Requires-Dist: numpy
Requires-Dist: pandas
Requires-Dist: pyarrow
Requires-Dist: pythonnet
Requires-Dist: ruamel-yaml
Requires-Dist: six
Requires-Dist: tqdm
